{
  "project_info": {
    "project_number": "349707998897",
    "firebase_url": "https://flatlay-9e497.firebaseio.com",
    "project_id": "flatlay-9e497",
    "storage_bucket": "flatlay-9e497.appspot.com"
  },
  "client": [
    {
      "client_info": {
        "mobilesdk_app_id": "1:349707998897:android:bf55f525166a0837",
        "android_client_info": {
          "package_name": "com.flatlay"
        }
      },
      "oauth_client": [
        {
          "client_id": "349707998897-9pmpkmflih02vv7vnbhp65m08omot9nn.apps.googleusercontent.com",
          "client_type": 3
        }
      ],
      "api_key": [
        {
          "current_key": "AIzaSyAHTzsvM-7f1dyJhshScZw44-n5ao8kw4s"
        }
      ],
      "services": {
        "analytics_service": {
          "status": 1
        },
        "appinvite_service": {
          "status": 1,
          "other_platform_oauth_client": []
        },
        "ads_service": {
          "status": 2
        }
      }
    }
  ],
  "configuration_version": "1"
}